traffic-light-fsm-evolution/v1_basic_fsm/traffic_light_fsm.v
module traffic_fsm( input clk,input rst,output reg [2:0]NS, output reg [2:0]EW);
//s0: NS=green EW=red;
//s1: NS=yellow EW=red;
//s2: NS=red EW=green;
//s3: NS=red EW=yellow;
localparam S0=2'b00;
localparam S1=2'b01;
localparam S2=2'b10;
localparam S3=2'b11;
localparam green=3'b001;
localparam yellow=3'b010;
localparam red=3'b100;
reg [1:0]present;
reg [1:0]next;
reg [3:0]count;

//present logic

always @(posedge clk)
begin
    if(rst==0)begin
    present<=S0;
    end
    else
    begin
     present<=next;     
    end
end

//counter

always@(posedge clk)
begin
    if(rst==0)begin
        count<=0;
    end
    else begin
        case(present)

        S0,S2:if(count==9)begin
            count<=0;
        end
        else begin
            count<=count+1;
        end
        S1,S3:if(count==2)begin
            count<=0;
        end
        else begin
            count<=count+1;
        end
        default: count<=0;
        endcase

    end
end

//next logic

always@(*)begin
    case(present)

    S0:next=(count==9)?S1:S0;
    S1:next=(count==2)?S2:S1;
    S2:next=(count==9)?S3:S2;
    S3:next=(count==2)?S0:S3;
    default:next=S0;

    endcase
end
//output
always@(*)begin
    case(present)
       S0:begin NS=green;EW=red;end
       S1:begin NS=yellow;EW=red; end
       S2:begin NS=red;EW=green; end
       S3:begin NS=red;EW=yellow; end
    default:begin NS=yellow;EW=yellow; end
    endcase
end

endmodule

traffic-light-fsm-evolution/v1_basic_fsm/traffic_light_tb.v
module traffic_fsm_tb;

reg clk;
reg rst;
wire [2:0] NS;
wire [2:0] EW;

// Instantiate DUT
traffic_fsm dut (.clk(clk),.rst(rst),.NS(NS),.EW(EW));

// Clock generation
always #5 clk = ~clk;

// Initial block
initial begin
clk = 0;
rst = 0;
#10 rst = 1;
// simulation limit
#500 $finish;

end

// Monitor outputs
initial begin
$monitor("Time=%0t | rst=%b | state=%b | count=%d | NS=%b | EW=%b",
         $time, rst, dut.present, dut.count, NS, EW);
end

// Dump waveform
initial begin
$dumpfile("traffic_fsm.vcd");
$dumpvars(0, traffic_fsm_tb);
end

endmodule

traffic-light-fsm-evolution/v1_basic_fsm/traffic_fsm.vcd
$date
	Tue Mar 24 12:04:44 2026
$end
$version
	Icarus Verilog
$end
$timescale
	1s
$end
$scope module traffic_fsm_tb $end
$var wire 3 ! NS [2:0] $end
$var wire 3 " EW [2:0] $end
$var reg 1 # clk $end
$var reg 1 $ rst $end
$scope module dut $end
$var wire 1 # clk $end
$var wire 1 $ rst $end
$var parameter 2 % S0 $end
$var parameter 2 & S1 $end
$var parameter 2 ' S2 $end
$var parameter 2 ( S3 $end
$var parameter 3 ) green $end
$var parameter 3 * red $end
$var parameter 3 + yellow $end
$var reg 3 , EW [2:0] $end
$var reg 3 - NS [2:0] $end
$var reg 4 . count [3:0] $end
$var reg 2 / next [1:0] $end
$var reg 2 0 present [1:0] $end
$upscope $end
$upscope $end
$enddefinitions $end
$comment Show the parameter values. $end
$dumpall
b10 +
b100 *
b1 )
b11 (
b10 '
b1 &
b0 %
$end
#0
$dumpvars
bx 0
bx /
bx .
bx -
bx ,
0$
0#
bx "
bx !
$end
#5
b100 "
b100 ,
b1 !
b1 -
b0 /
b0 0
b0 .
1#
#10
0#
1$
#15
b1 .
1#
#20
0#
#25
b10 .
1#
#30
0#
#35
b11 .
1#
#40
0#
#45
b100 .
1#
#50
0#
#55
b101 .
1#
#60
0#
#65
b110 .
1#
#70
0#
#75
b111 .
1#
#80
0#
#85
b1000 .
1#
#90
0#
#95
b1 /
b1001 .
1#
#100
0#
#105
b10 !
b10 -
b1 0
b0 .
1#
#110
0#
#115
b1 .
1#
#120
0#
#125
b10 /
b10 .
1#
#130
0#
#135
b1 "
b1 ,
b100 !
b100 -
b0 .
b10 0
1#
#140
0#
#145
b1 .
1#
#150
0#
#155
b10 .
1#
#160
0#
#165
b11 .
1#
#170
0#
#175
b100 .
1#
#180
0#
#185
b101 .
1#
#190
0#
#195
b110 .
1#
#200
0#
#205
b111 .
1#
#210
0#
#215
b1000 .
1#
#220
0#
#225
b11 /
b1001 .
1#
#230
0#
#235
b10 "
b10 ,
b0 .
b11 0
1#
#240
0#
#245
b1 .
1#
#250
0#
#255
b0 /
b10 .
1#
#260
0#
#265
b100 "
b100 ,
b1 !
b1 -
b0 0
b0 .
1#
#270
0#
#275
b1 .
1#
#280
0#
#285
b10 .
1#
#290
0#
#295
b11 .
1#
#300
0#
#305
b100 .
1#
#310
0#
#315
b101 .
1#
#320
0#
#325
b110 .
1#
#330
0#
#335
b111 .
1#
#340
0#
#345
b1000 .
1#
#350
0#
#355
b1 /
b1001 .
1#
#360
0#
#365
b10 !
b10 -
b1 0
b0 .
1#
#370
0#
#375
b1 .
1#
#380
0#
#385
b10 /
b10 .
1#
#390
0#
#395
b1 "
b1 ,
b100 !
b100 -
b0 .
b10 0
1#
#400
0#
#405
b1 .
1#
#410
0#
#415
b10 .
1#
#420
0#
#425
b11 .
1#
#430
0#
#435
b100 .
1#
#440
0#
#445
b101 .
1#
#450
0#
#455
b110 .
1#
#460
0#
#465
b111 .
1#
#470
0#
#475
b1000 .
1#
#480
0#
#485
b11 /
b1001 .
1#
#490
0#
#495
b10 "
b10 ,
b0 .
b11 0
1#
#500
0#
#505
b1 .
1#
